{
    "Ar36": {
        "error": 0.00011590941894697621,
        "error_type": "SEM",
        "filter_outliers_dict": {
            "filter_outliers": true,
            "iterations": 1,
            "std_devs": 3,
            "use_iqr_filtering": false,
            "use_standard_deviation_filtering": false
        },
        "fit": "linear",
        "fn": 597,
        "include_baseline_error": true,
        "n": 600,
        "outlier_excluded": [
            0,
            281,
            472
        ],
        "reviewed": true,
        "user_excluded": [],
        "value": 0.008020355461790385
    },
    "Ar37": {
        "error": 0.00438103557074321,
        "error_type": "SEM",
        "filter_outliers_dict": {
            "filter_outliers": true,
            "iterations": 1,
            "std_devs": 3,
            "use_iqr_filtering": false,
            "use_standard_deviation_filtering": false
        },
        "fit": "linear",
        "fn": 598,
        "include_baseline_error": true,
        "n": 600,
        "outlier_excluded": [
            329,
            244
        ],
        "reviewed": true,
        "user_excluded": [],
        "value": 0.0248417304935043
    },
    "Ar38": {
        "error": 0.0021565775538774697,
        "error_type": "SEM",
        "filter_outliers_dict": {
            "filter_outliers": true,
            "iterations": 1,
            "std_devs": 3,
            "use_iqr_filtering": false,
            "use_standard_deviation_filtering": false
        },
        "fit": "linear",
        "fn": 597,
        "include_baseline_error": true,
        "n": 600,
        "outlier_excluded": [
            0,
            1,
            2
        ],
        "reviewed": true,
        "user_excluded": [],
        "value": 0.1203981391949919
    },
    "Ar39": {
        "error": 0.008374309092735961,
        "error_type": "SEM",
        "filter_outliers_dict": {
            "filter_outliers": true,
            "iterations": 1,
            "std_devs": 3,
            "use_iqr_filtering": false,
            "use_standard_deviation_filtering": false
        },
        "fit": "parabolic",
        "fn": 597,
        "include_baseline_error": true,
        "n": 600,
        "outlier_excluded": [
            0,
            66,
            485
        ],
        "reviewed": true,
        "user_excluded": [],
        "value": 4.461245185840203
    },
    "Ar40": {
        "error": 0.015410577586192438,
        "error_type": "SEM",
        "filter_outliers_dict": {
            "filter_outliers": true,
            "iterations": 1,
            "std_devs": 3,
            "use_iqr_filtering": false,
            "use_standard_deviation_filtering": false
        },
        "fit": "parabolic",
        "fn": 598,
        "include_baseline_error": true,
        "n": 600,
        "outlier_excluded": [
            14,
            15
        ],
        "reviewed": true,
        "user_excluded": [],
        "value": 22.650733977325636
    },
    "Ar41": {
        "error": 0.0017909852889588275,
        "error_type": "SEM",
        "filter_outliers_dict": {
            "filter_outliers": true,
            "iterations": 1,
            "std_devs": 2
        },
        "fit": "linear",
        "value": -0.008814859629452308
    }
}